tiktokrocket/__init__.py
tiktokrocket/data/__init__.py
tiktokrocket/data/config.py
tiktokrocket/utils/__init__.py
tiktokrocket/utils/sms/__init__.py
tiktokrocket/utils/sms/base.py
tiktokrocket/utils/sms/grizzly.py
tiktokrocket/utils/types/__init__.py
tiktokrocket/utils/types/browser.py
tiktokrocket/utils/types/client.py
tiktokrocket/utils/types/env.py
tiktokrocket/utils/types/tiktokrocket.py
tiktokrocket/utils/types/ui_window.py
tiktokrocket/utils/types/updater.py
tiktokrocket-1.1.8.dist-info/METADATA
tiktokrocket-1.1.8.dist-info/WHEEL
tiktokrocket-1.1.8.dist-info/RECORD
