Metadata-Version: 2.3
Name: tiktokrocket
Version: 1.1.8
Summary: 
Author: eugconrad
Requires-Python: >=3.11
Classifier: Programming Language :: Python :: 3
Classifier: Programming Language :: Python :: 3.11
Classifier: Programming Language :: Python :: 3.12
Classifier: Programming Language :: Python :: 3.13
Requires-Dist: aiohttp (>=3.11.16,<4.0.0)
Requires-Dist: blinker (==1.7.0)
Requires-Dist: loguru (>=0.7.3,<0.8.0)
Requires-Dist: platformdirs (>=4.3.7,<5.0.0)
Requires-Dist: python-dotenv (>=1.0.1,<2.0.0)
Requires-Dist: requests (>=2.32.3,<3.0.0)
Requires-Dist: selenium (==4.23.0)
Requires-Dist: selenium-stealth (==1.0.6)
Requires-Dist: selenium-wire (==5.1.0)
Requires-Dist: setuptools (>=75.8.0,<76.0.0)
Requires-Dist: ua-generator (>=2.0.5,<3.0.0)
Requires-Dist: undetected-chromedriver (==3.5.5)
